wunderscout/__init__.py
wunderscout/core.py
wunderscout/data.py
wunderscout/exporters.py
wunderscout/geometry.py
wunderscout/heatmaps.py
wunderscout/models.py
wunderscout/pass_network.py
wunderscout/teams.py
wunderscout-0.1.15.dist-info/METADATA
wunderscout-0.1.15.dist-info/WHEEL
wunderscout-0.1.15.dist-info/RECORD
