Metadata-Version: 2.4
Name: wunderscout
Version: 0.1.15
Summary: Scouting and vision tools for YOLO and sports analytics.
Project-URL: Homepage, https://github.com/qhuboo/wunderscout
Project-URL: Issues, https://github.com/qhuboo/wunderscout/issues
Keywords: scouting,sports-analytics,vision,yolo
Classifier: License :: OSI Approved :: MIT License
Classifier: Operating System :: OS Independent
Classifier: Programming Language :: Python :: 3
Requires-Python: >=3.11
Requires-Dist: matplotlib>=3.10.6
Requires-Dist: more-itertools>=10.8.0
Requires-Dist: networkx>=3.5
Requires-Dist: numpy>=2.3.2
Requires-Dist: opencv-python>=4.11.0.86
Requires-Dist: pandas>=2.3.2
Requires-Dist: protobuf>=6.33.4
Requires-Dist: python-dotenv>=1.1.1
Requires-Dist: roboflow>=1.2.7
Requires-Dist: scikit-learn>=1.7.2
Requires-Dist: scipy>=1.16.2
Requires-Dist: seaborn>=0.13.2
Requires-Dist: sentencepiece>=0.2.1
Requires-Dist: supervision>=0.26.1
Requires-Dist: torch>=2.8.0
Requires-Dist: tqdm>=4.67.1
Requires-Dist: transformers>=4.56.1
Requires-Dist: ultralytics>=8.3.193
Requires-Dist: umap-learn>=0.5.9.post2
